Metadata-Version: 2.1
Name: diogi
Version: 0.1.0
Summary: A library of tiny little functions to make development that little bit easier.
Home-page: https://github.com/michalporeba/diogi
Author: Michal Poreba
License: MIT
Platform: UNKNOWN
Classifier: Development Status :: 3 - Alpha
Classifier: License :: OSI Approved :: MIT License
Classifier: Programming Language :: Python :: 3
Classifier: Intended Audience :: Developers
Classifier: Topic :: Software Development
License-File: LICENSE
